nPrimos_sLopez/__init__.py
nPrimos_sLopez/codigo_rpy2_SergioLopez.py
nPrimos_sLopez-1.0.dist-info/LICENSE
nPrimos_sLopez-1.0.dist-info/METADATA
nPrimos_sLopez-1.0.dist-info/WHEEL
nPrimos_sLopez-1.0.dist-info/top_level.txt
nPrimos_sLopez-1.0.dist-info/RECORD
